SBExchange/Exchange.py
SBExchange/__init__.py
SBExchange-0.21.dist-info/METADATA
SBExchange-0.21.dist-info/WHEEL
SBExchange-0.21.dist-info/top_level.txt
SBExchange-0.21.dist-info/RECORD
