Metadata-Version: 2.1
Name: SBExchange
Version: 0.21
